cdpop.py
cdpop-1.0.0.dist-info/LICENSE
cdpop-1.0.0.dist-info/METADATA
cdpop-1.0.0.dist-info/WHEEL
cdpop-1.0.0.dist-info/entry_points.txt
cdpop-1.0.0.dist-info/top_level.txt
cdpop-1.0.0.dist-info/RECORD
