Metadata-Version: 2.1
Name: cdpop
Version: 1.0.0
Summary: Pop open cash drawer with http GET request
Author-email: Nathan Fraser <ndf-zz@6-v.org>
License: MIT
Project-URL: homepage, https://github.com/ndf-zz/cdpop
Keywords: tornado
Classifier: Development Status :: 3 - Alpha
Classifier: Topic :: Office/Business :: Financial :: Point-Of-Sale
Classifier: Operating System :: OS Independent
Classifier: Programming Language :: Python :: 3
Requires-Python: >=3.9
License-File: LICENSE
Requires-Dist: posiflex-hidcd
Requires-Dist: tornado
